DEVELOPMENT.md
Dockerfile
HISTORY.md
LICENSE
MANIFEST.in
README.md
docker-compose.yml
manage.py
requirements-dev.txt
setup.cfg
setup.py
conf/certs/.empty
conf/nginx/default.conf
django_push_redirect.egg-info/PKG-INFO
django_push_redirect.egg-info/SOURCES.txt
django_push_redirect.egg-info/dependency_links.txt
django_push_redirect.egg-info/not-zip-safe
django_push_redirect.egg-info/requires.txt
django_push_redirect.egg-info/top_level.txt
push_redirect/__init__.py
push_redirect/middleware.py
tests/__init__.py
tests/settings.py
tests/test_middleware.py
tests/urls.py
tests/wsgi.py