Metadata-Version: 2.1
Name: django-push-redirect
Version: 1.1.0
Summary: A Django middleware that adds a HTTP/2 Server Push header to plain Django redirect responses
Home-page: https://github.com/leukeleu/django-push-redirect
Author: Jaap Roes (Leukeleu)
Author-email: jroes@leukeleu.nl
License: BSD-3-Clause
Project-URL: Documentation, https://github.com/leukeleu/django-push-redirect
Project-URL: Source, https://github.com/leukeleu/django-push-redirect
Project-URL: Tracker, https://github.com/leukeleu/django-push-redirect/issues
Keywords: django http2 server push redirect preload
Platform: UNKNOWN
Classifier: Environment :: Web Environment
Classifier: Framework :: Django
Classifier: Intended Audience :: Developers
Classifier: License :: OSI Approved :: BSD License
Classifier: Operating System :: OS Independent
Classifier: Programming Language :: Python
Classifier: Programming Language :: Python :: 3
Classifier: Programming Language :: Python :: 3 :: Only
Classifier: Programming Language :: Python :: 3.6
Classifier: Programming Language :: Python :: 3.7
Classifier: Programming Language :: Python :: 3.8
Classifier: Development Status :: 5 - Production/Stable
Requires-Python: >=3.6
